{
  "name": "PDF Compressor Workflow",
  "nodes": [
    {
      "parameters": {},
      "name": "Manual Trigger",
      "type": "n8n-nodes-base.manualTrigger",
      "typeVersion": 1,
      "position": [250, 300]
    },
    {
      "parameters": {
        "url": "http://localhost:3000/api/pdf",
        "sendBody": true,
        "bodyParameters": {
          "parameters": [
            {
              "name": "compression",
              "value": "75"
            }
          ]
        },
        "sendHeaders": true,
        "options": {
          "response": {
            "response": {
              "responseFormat": "file"
            }
          }
        }
      },
      "name": "Compress PDF",
      "type": "n8n-nodes-base.httpRequest",
      "typeVersion": 4.1,
      "position": [450, 300]
    }
  ],
  "connections": {
    "Manual Trigger": {
      "main": [
        [
          {
            "node": "Compress PDF",
            "type": "main",
            "index": 0
          }
        ]
      ]
    }
  }
}

